mdk_runtime_files.py
quark_runtime.py
quark_runtime_logging.py
quark_threaded_runtime.py
quark_ws4py_fixup.py
datawire_mdk-2.0.37.dist-info/DESCRIPTION.rst
datawire_mdk-2.0.37.dist-info/METADATA
datawire_mdk-2.0.37.dist-info/RECORD
datawire_mdk-2.0.37.dist-info/WHEEL
datawire_mdk-2.0.37.dist-info/metadata.json
datawire_mdk-2.0.37.dist-info/top_level.txt
datawire_mdk_md/__init__.py
mdk/__init__.py
mdk/django.py
mdk/flask.py
mdk/logging.py
mdk/requests.py
mdk_discovery/__init__.py
mdk_discovery/protocol/__init__.py
mdk_discovery/synapse/__init__.py
mdk_introspection/__init__.py
mdk_introspection/aws/__init__.py
mdk_introspection/kubernetes/__init__.py
mdk_metrics/__init__.py
mdk_protocol/__init__.py
mdk_rtp/__init__.py
mdk_runtime/__init__.py
mdk_runtime/actors/__init__.py
mdk_runtime/files/__init__.py
mdk_runtime/promise/__init__.py
mdk_tracing/__init__.py
mdk_tracing/api/__init__.py
mdk_tracing/protocol/__init__.py
mdk_util/__init__.py
quark/__init__.py
quark/behaviors/__init__.py
quark/concurrent/__init__.py
quark/error/__init__.py
quark/logging/__init__.py
quark/mock/__init__.py
quark/os/__init__.py
quark/reflect/__init__.py
quark/spi/__init__.py
quark/spi_api/__init__.py
quark/spi_api_tracing/__init__.py
quark/test/__init__.py
