Metadata-Version: 2.0
Name: datawire-mdk
Version: 2.0.37
Summary: The Microservices Development Kit (MDK)
Home-page: https://www.datawire.io
Author: Datawire.io
Author-email: UNKNOWN
License: Apache-2.0
Platform: UNKNOWN
Requires-Dist: blinker (==1.4)
Requires-Dist: future (==0.15.2)
Requires-Dist: wheel
Requires-Dist: ws4py (==0.3.4)
